  [
  {
  "CountryId": "1",
  "CountryName": "استرالیا",
  "CountryFlag": "australia",
"CountryLat" : "35.3080",
"CountryLng":"149.1245"
  },
  {
  "CountryId": "2",
  "CountryName": "فیجی",
  "CountryFlag" : "fiji",
"CountryLat" : "18.0000",
"CountryLng":"179.0000"
  },
  {
  "CountryId": "3",
  "CountryName": "گرینلند",
  "CountryFlag" : "greenland",
  "CountryLat" : "72.0000",
"CountryLng":"40.0000"
  },
  {
  "CountryId": "4",
  "CountryName": "گرنادا",
  "CountryFlag" : "grenada",
 "CountryLat" : "12.0500",
"CountryLng":"61.7500"
  },
  {
  "CountryId": "5",
  "CountryName": "کیریباتی",
  "CountryFlag" : "kiribati",
  "CountryLat" : "1.4667",
"CountryLng":"173.0333"
  },
  {
  "CountryId": "6",
  "CountryName": "ماداگاسکار",
  "CountryFlag" : "madagascar",
  "CountryLat" : "20.0000",
"CountryLng":"47.0000"
  },
  {
  "CountryId": "7",
  "CountryName": "مالدیو",
  "CountryFlag" : "mali",
  "CountryLat" : "12.6500",
"CountryLng":"8.0000"
  },
  {
  "CountryId": "8",
  "CountryName": "جزایر مارشال",
  "CountryFlag" : "marshallislands",
  "CountryLat" : "7.0667",
"CountryLng":"171.2667"
  },
  {
  "CountryId": "9",
  "CountryName": "موریس",
  "CountryFlag" : "mauritius",
  "CountryLat" : "20.2000",
"CountryLng":"57.5000"
  },
  {
  "CountryId": "10",
  "CountryName": "میکرونزی",
  "CountryFlag" : "micronesia",
 "CountryLat" : "6.9167",
"CountryLng":"158.1833"
  },
  {
  "CountryId": "11",
  "CountryName": "نائورو",
  "CountryFlag" : "nauru",
 "CountryLat" : "0.5333",
"CountryLng":"166.9333"
  },
  {
  "CountryId": "12",
  "CountryName": "نیوزلند",
  "CountryFlag" : "newzealand",
  "CountryLat" : "42.0000",
"CountryLng":"174.0000"
  },
  {
  "CountryId": "13",
  "CountryName": "پاپوا گینه نو",
  "CountryFlag" : "papuanewguinea",
  "CountryLat" : "9.5000",
"CountryLng":"147.1167"
  },
  {
  "CountryId": "14",
  "CountryName": "ساموآ",
  "CountryFlag" : "samoa",
  "CountryLat" : "13.8333",
"CountryLng":"171.7500"
  },
  {
  "CountryId": "15",
  "CountryName": "تونگا",
  "CountryFlag" : "tonga",
  "CountryLat" : "21.1333",
"CountryLng":"175.2000"
  },
  {
  "CountryId": "16",
  "CountryName": "تووالو",
  "CountryFlag" : "tuvalu",
 "CountryLat" : "8.5333",
"CountryLng":"179.2167"
  },
  {
  "CountryId": "17",
  "CountryName": "وانواتو",
  "CountryFlag" : "vanutau",
  "CountryLat" : "17.7500",
"CountryLng":"168.3000"
  }
  ]